{
  "project_info": {
    "project_number": "534128909934",
    "project_id": "chatify-87928",
    "storage_bucket": "chatify-87928.appspot.com"
  },
  "client": [
    {
      "client_info": {
        "mobilesdk_app_id": "1:534128909934:android:a567d385043ed6ab7f107f",
        "android_client_info": {
          "package_name": "com.example.chatify"
        }
      },
      "oauth_client": [
        {
          "client_id": "534128909934-smh561s9bg89kk6b7m83vcho0cp36shd.apps.googleusercontent.com",
          "client_type": 3
        }
      ],
      "api_key": [
        {
          "current_key": "AIzaSyCam-SHb17ds9pn_s-FkS-zVh7S8bokHL4"
        }
      ],
      "services": {
        "appinvite_service": {
          "other_platform_oauth_client": [
            {
              "client_id": "534128909934-smh561s9bg89kk6b7m83vcho0cp36shd.apps.googleusercontent.com",
              "client_type": 3
            },
            {
              "client_id": "534128909934-044kf9npa0omset0h9853q9qds9upg5p.apps.googleusercontent.com",
              "client_type": 2,
              "ios_info": {
                "bundle_id": "com.example.chatify"
              }
            }
          ]
        }
      }
    }
  ],
  "configuration_version": "1"
}